mensetmanus/__init__.py
mensetmanus/tts.py
mensetmanus/visuals.py
mensetmanus/widgets/__init__.py
mensetmanus/widgets/javascript/photo.js
mensetmanus/widgets/javascript/timer.js
mensetmanus/widgets/javascript/toast.js
mensetmanus/widgets/javascript/volume.js
mensetmanus-0.1.1.dist-info/METADATA
mensetmanus-0.1.1.dist-info/WHEEL
mensetmanus-0.1.1.dist-info/RECORD
